machlearn/__about__.py
machlearn/__init__.py
machlearn/DSA/_DSA.py
machlearn/DSA/__init__.py
machlearn/DSA/_sorting_and_searching.py
machlearn/DSA/_trees_and_graphs.py
machlearn/SVM/_SVM.py
machlearn/SVM/__init__.py
machlearn/datasets/__init__.py
machlearn/datasets/_dataset_methods.py
machlearn/datasets/_datasets.py
machlearn/datasets/public/.DS_Store
machlearn/datasets/public/README.txt
machlearn/datasets/public/Fashion_MNIST/LICENSE
machlearn/datasets/public/Fashion_MNIST/README.txt
machlearn/datasets/public/Fashion_MNIST/t10k-images-idx3-ubyte.gz
machlearn/datasets/public/Fashion_MNIST/t10k-labels-idx1-ubyte.gz
machlearn/datasets/public/Fashion_MNIST/train-images-idx3-ubyte.gz
machlearn/datasets/public/Fashion_MNIST/train-labels-idx1-ubyte.gz
machlearn/datasets/public/ML_for_Hackers/01_heights_weights_genders.csv
machlearn/datasets/public/ML_for_Hackers/License_info.pdf
machlearn/datasets/public/R_ISLR/ISLR.pdf
machlearn/datasets/public/R_ISLR/Hitters/Hitters.csv
machlearn/datasets/public/R_datarium/datarium.pdf
machlearn/datasets/public/R_datarium/marketing/marketing.csv
machlearn/datasets/public/Social_Network_Ads/Social_Network_Ads.csv
machlearn/datasets/public/UCI_Machine_Learning_Repository/Citation Policy.pdf
machlearn/datasets/public/UCI_Machine_Learning_Repository/SMS_Spam_Collection/SMSSpamCollection.tsv
machlearn/datasets/public/UCI_Machine_Learning_Repository/SMS_Spam_Collection/readme
machlearn/datasets/public/UCI_Machine_Learning_Repository/bank_note_authentication/data_banknote_authentication.txt
machlearn/datasets/public/nltk_data/corpora/wordnet/LICENSE
machlearn/datasets/public/nltk_data/corpora/wordnet/README
machlearn/datasets/public/nltk_data/corpora/wordnet/adj.exc
machlearn/datasets/public/nltk_data/corpora/wordnet/adv.exc
machlearn/datasets/public/nltk_data/corpora/wordnet/citation.bib
machlearn/datasets/public/nltk_data/corpora/wordnet/cntlist.rev
machlearn/datasets/public/nltk_data/corpora/wordnet/data.adj
machlearn-1.2.14.dist-info/LICENSE
machlearn-1.2.14.dist-info/METADATA
machlearn-1.2.14.dist-info/WHEEL
machlearn-1.2.14.dist-info/top_level.txt
machlearn-1.2.14.dist-info/RECORD
