Metadata-Version: 2.1
Name: machlearn
Version: 1.2.14
Summary: Machine Learning Python Library
Home-page: https://github.com/daniel-yj-yang/machlearn
Author: Daniel Yang
Author-email: daniel.yj.yang@gmail.com
License: BSD 3-Clause
Platform: UNKNOWN
Classifier: Topic :: Scientific/Engineering
Classifier: Programming Language :: Python :: 3
Classifier: Programming Language :: Python :: 3.6
Classifier: Programming Language :: Python :: 3.7
Classifier: Programming Language :: Python :: 3.8
Classifier: License :: OSI Approved :: BSD License
Classifier: Operating System :: OS Independent
Requires-Python: >=3.6
Requires-Dist: scikit-learn (>=0.23.2)
Requires-Dist: numpy (>=1.19.2)
Requires-Dist: seaborn (>=0.11.0)
Requires-Dist: matplotlib (>=3.3.2)
Requires-Dist: pandas (>=1.1.2)
Requires-Dist: textblob (>=0.15.3)
Requires-Dist: nltk (>=3.5)
Requires-Dist: pydotplus (>=2.0.2)
Requires-Dist: dtreeviz (>=1.1.2)
Requires-Dist: statsmodels (>=0.12.0)
Requires-Dist: sortedcontainers (>=2.2.2)
